hickle/__init__.py
hickle/__version__.py
hickle/fileio.py
hickle/helpers.py
hickle/hickle.py
hickle/lookup.py
hickle/legacy_v3/__init__.py
hickle/legacy_v3/__version__.py
hickle/legacy_v3/helpers.py
hickle/legacy_v3/hickle.py
hickle/legacy_v3/lookup.py
hickle/legacy_v3/loaders/__init__.py
hickle/legacy_v3/loaders/load_astropy.py
hickle/legacy_v3/loaders/load_numpy.py
hickle/legacy_v3/loaders/load_pandas.py
hickle/legacy_v3/loaders/load_python3.py
hickle/legacy_v3/loaders/load_scipy.py
hickle/loaders/__init__.py
hickle/loaders/load_astropy.py
hickle/loaders/load_builtins.py
hickle/loaders/load_numpy.py
hickle/loaders/load_pandas.py
hickle/loaders/load_scipy.py
hickle/tests/__init__.py
hickle/tests/generate_legacy_4_0_0.py
hickle/tests/test_01_hickle_helpers.py
hickle/tests/test_02_hickle_lookup.py
hickle/tests/test_03_load_builtins.py
hickle/tests/test_04_load_numpy.py
hickle/tests/test_05_load_scipy.py
hickle/tests/test_06_load_astropy.py
hickle/tests/test_07_load_pandas.py
hickle/tests/test_99_hickle_core.py
hickle/tests/test_hickle.py
hickle/tests/test_legacy_load.py
hickle/tests/hickle_loaders/__init__.py
hickle/tests/hickle_loaders/load_builtins.py
hickle-5.0.3.dist-info/LICENSE
hickle-5.0.3.dist-info/METADATA
hickle-5.0.3.dist-info/WHEEL
hickle-5.0.3.dist-info/top_level.txt
hickle-5.0.3.dist-info/RECORD
