Metadata-Version: 2.1
Name: hickle
Version: 5.0.3
Summary: Hickle - an HDF5 based version of pickle
Home-page: http://github.com/telegraphic/hickle
Download-URL: https://github.com/telegraphic/hickle/archive/v5.0.3.zip
Author: Danny Price, Ellert van der Velden and contributors
Author-email: dan@thetelegraphic.com
Keywords: pickle,hdf5,data storage,data export
Platform: Cross platform (Linux
Platform: Mac OSX
Platform: Windows)
Classifier: Development Status :: 5 - Production/Stable
Classifier: Intended Audience :: Developers
Classifier: Intended Audience :: Science/Research
Classifier: License :: OSI Approved
Classifier: Natural Language :: English
Classifier: Operating System :: MacOS
Classifier: Operating System :: Microsoft :: Windows
Classifier: Operating System :: Unix
Classifier: Programming Language :: Python
Classifier: Programming Language :: Python :: 3
Classifier: Programming Language :: Python :: 3.7
Classifier: Programming Language :: Python :: 3.8
Classifier: Programming Language :: Python :: 3.9
Classifier: Programming Language :: Python :: 3.10
Classifier: Programming Language :: Python :: 3.11
Classifier: Topic :: Software Development :: Libraries :: Python Modules
Classifier: Topic :: Utilities
Requires-Python: >=3.7
License-File: LICENSE
Requires-Dist: h5py>=2.10.0
Requires-Dist: numpy!=1.20,>=1.8
